kedro_auto_catalog/__about__.py
kedro_auto_catalog/__init__.py
kedro_auto_catalog/cli.py
kedro_auto_catalog-0.2.0.dist-info/METADATA
kedro_auto_catalog-0.2.0.dist-info/WHEEL
kedro_auto_catalog-0.2.0.dist-info/entry_points.txt
kedro_auto_catalog-0.2.0.dist-info/licenses/LICENSE.txt
kedro_auto_catalog-0.2.0.dist-info/RECORD
