Metadata-Version: 2.1
Name: kedro-auto-catalog
Version: 0.2.0
Summary: A configurable replacement for `kedro catalog create`.
Project-URL: Documentation, https://github.com/waylonwalker/kedro-auto-catalog#readme
Project-URL: Issues, https://github.com/waylonwalker/kedro-auto-catalog/issues
Project-URL: Source, https://github.com/waylonwalker/kedro-auto-catalog
Project-URL: Changelog, https://github.com/waylonwalker/kedro-auto-catalog
Author-email: "Waylon S. Walker" <waylon@waylonwalker.com>
License-Expression: MIT
License-File: LICENSE.txt
Classifier: Development Status :: 4 - Beta
Classifier: Programming Language :: Python
Classifier: Programming Language :: Python :: 3.7
Classifier: Programming Language :: Python :: 3.8
Classifier: Programming Language :: Python :: 3.9
Classifier: Programming Language :: Python :: 3.10
Classifier: Programming Language :: Python :: 3.11
Classifier: Programming Language :: Python :: Implementation :: CPython
Classifier: Programming Language :: Python :: Implementation :: PyPy
Requires-Python: >=3.7
Requires-Dist: kedro
Requires-Dist: rich
